url_generator/__init__.py
url_generator-1.1.1.dist-info/LICENSE
url_generator-1.1.1.dist-info/METADATA
url_generator-1.1.1.dist-info/WHEEL
url_generator-1.1.1.dist-info/top_level.txt
url_generator-1.1.1.dist-info/RECORD
