Metadata-Version: 2.1
Name: url-generator
Version: 1.1.1
Summary: Universal URL generator.
Home-page: https://github.com/heureka/py-url-generator
Author: Heureka.cz
Author-email: vyvoj@heureka.cz
License: Apache
License-File: LICENSE
